laserfarm/__init__.py
laserfarm/__version__.py
laserfarm/classification.py
laserfarm/data_processing.py
laserfarm/geotiff_writer.py
laserfarm/grid.py
laserfarm/logger.py
laserfarm/macro_pipeline.py
laserfarm/main.py
laserfarm/pipeline.py
laserfarm/pipeline_remote_data.py
laserfarm/remote_utils.py
laserfarm/retiler.py
laserfarm/utils.py
laserfarm-0.3.1.dist-info/licenses/LICENSE
laserfarm-0.3.1.dist-info/METADATA
laserfarm-0.3.1.dist-info/WHEEL
laserfarm-0.3.1.dist-info/entry_points.txt
laserfarm-0.3.1.dist-info/top_level.txt
laserfarm-0.3.1.dist-info/RECORD
