Metadata-Version: 2.4
Name: laserfarm
Version: 0.3.1
Summary: Laserchicken Framework for Applications in Research in Macro-ecology
Author-email: Netherlands eScience Center <team-atlas@esciencecenter.nl>
License-Expression: Apache-2.0
Project-URL: repository, https://github.com/eEcoLiDAR/Laserfarm
Project-URL: documentation, https://laserfarm.readthedocs.io
Project-URL: changelog, https://github.com/eEcoLiDAR/Laserfarm/blob/master/CHANGELOG.md
Project-URL: doi, https://doi.org/10.5281/zenodo.3842780
Keywords: Python,Point cloud
Classifier: Development Status :: 2 - Pre-Alpha
Classifier: Intended Audience :: Developers
Classifier: Natural Language :: English
Classifier: Programming Language :: Python :: 3
Classifier: Programming Language :: Python :: 3.10
Classifier: Programming Language :: Python :: 3.11
Classifier: Programming Language :: Python :: 3.12
License-File: LICENSE
Requires-Dist: asyncssh
Requires-Dist: dask[complete]
Requires-Dist: fire
Requires-Dist: numpy
Requires-Dist: laspy[lazrs]
Requires-Dist: laserchicken>=0.6.0
Requires-Dist: plyfile
Requires-Dist: webdavclient3
Requires-Dist: PyShp
Requires-Dist: shapely
Provides-Extra: dev
Requires-Dist: pytest>=6.0; extra == "dev"
Requires-Dist: pytest-cov; extra == "dev"
Requires-Dist: pycodestyle; extra == "dev"
Requires-Dist: pyproj; extra == "dev"
Provides-Extra: docs
Requires-Dist: sphinx; extra == "docs"
Requires-Dist: m2r2; extra == "docs"
Dynamic: license-file
